geobank/__init__.py
geobank/apps.py
geobank/constants.py
geobank/converters.py
geobank/downloaders.py
geobank/enums.py
geobank/models.py
geobank/parsers.py
geobank/populators.py
geobank/tasks.py
geobank/translation.py
geobank/utils.py
geobank/management/__init__.py
geobank/management/commands/__init__.py
geobank/management/commands/populate_geobank.py
geobank/migrations/0001_initial.py
geobank/migrations/__init__.py
geobank/tests/__init__.py
geobank/tests/conftest.py
geobank/tests/settings.py
geobank/tests/test_constants.py
geobank/tests/test_downloaders.py
geobank/tests/test_integration.py
geobank/tests/test_models.py
geobank/tests/test_parsers.py
geobank/tests/test_populators.py
geobank-1.1.1.dist-info/licenses/LICENSE
geobank-1.1.1.dist-info/METADATA
geobank-1.1.1.dist-info/WHEEL
geobank-1.1.1.dist-info/top_level.txt
geobank-1.1.1.dist-info/RECORD
